LICENSE
README.md
pyproject.toml
setup.py
scripts/oldProteinIC.py
scripts/update_rotlib.py
src/chilife/FluorLabel.py
src/chilife/IntrinsicLabel.py
src/chilife/MolSys.py
src/chilife/MolSysIC.py
src/chilife/RotamerEnsemble.py
src/chilife/SpinLabel.py
src/chilife/SpinLabelTraj.py
src/chilife/Topology.py
src/chilife/__init__.py
src/chilife/alignment_methods.py
src/chilife/chilife.py
src/chilife/dRotamerEnsemble.py
src/chilife/dSpinLabel.py
src/chilife/globals.py
src/chilife/io.py
src/chilife/math_utils.py
src/chilife/numba_utils.py
src/chilife/pdb_utils.py
src/chilife/protein_utils.py
src/chilife/scoring.py
src/chilife.egg-info/PKG-INFO
src/chilife.egg-info/SOURCES.txt
src/chilife.egg-info/dependency_links.txt
src/chilife.egg-info/requires.txt
src/chilife.egg-info/top_level.txt
src/chilife/data/BondDefs.pkl
src/chilife/data/atom_dict
src/chilife/data/dihedral_defs.json
src/chilife/data/dihedral_defs.toml
src/chilife/data/mplstyles/chiLife.mplstyle
src/chilife/data/rotamer_libraries/ALL.bbdep.rotamers.lib
src/chilife/data/rotamer_libraries/BBDEP2010_LICENSE
src/chilife/data/rotamer_libraries/IndexBBDep.py
src/chilife/data/rotamer_libraries/R1C.lib
src/chilife/data/rotamer_libraries/RotlibIndexes.pkl
src/chilife/data/rotamer_libraries/additional_rotlib_dirs.txt
src/chilife/data/rotamer_libraries/bbdep.db
src/chilife/data/rotamer_libraries/ccaps.txt
src/chilife/data/rotamer_libraries/defaults.toml
src/chilife/data/rotamer_libraries/make_bbdep_rotlib.py
src/chilife/data/rotamer_libraries/make_rotlib.py
src/chilife/data/rotamer_libraries/ncaps.txt
src/chilife/data/rotamer_libraries/spin_atoms.json
src/chilife/data/rotamer_libraries/cap_pdbs/ACE.pdb
src/chilife/data/rotamer_libraries/cap_pdbs/NME.pdb
src/chilife/data/rotamer_libraries/residue_internal_coords/I1M_ic.pkl
src/chilife/data/rotamer_libraries/residue_internal_coords/ala_ic.pkl
src/chilife/data/rotamer_libraries/residue_internal_coords/arg_ic.pkl
src/chilife/data/rotamer_libraries/residue_internal_coords/ash_ic.pkl
src/chilife/data/rotamer_libraries/residue_internal_coords/asn_ic.pkl
src/chilife/data/rotamer_libraries/residue_internal_coords/asp_ic.pkl
