Metadata-Version: 2.4
Name: chilife
Version: 1.1.7
Summary: A package for modeling non-canonical amino acid side chain ensembles.
Author-email: Maxx Tessmer <mhtessmer@gmail.com>, Stefan Stoll <stst@uw.edu>
License:                     GNU GENERAL PUBLIC LICENSE
Project-URL: homepage, https://github.com/StollLab/chiLife
Project-URL: documentation, https://stolllab.github.io/chiLife/
Keywords: Spin-label,EPR,DEER,PELDOR,Side-chain
Classifier: License :: OSI Approved :: GNU General Public License v3 (GPLv3)
Classifier: Programming Language :: Python :: 3.8
Classifier: Programming Language :: Python :: 3.9
Classifier: Programming Language :: Python :: 3.10
Classifier: Programming Language :: Python :: 3.11
Classifier: Programming Language :: Python :: 3.12
Requires-Python: <3.14,>=3.8
License-File: LICENSE
Requires-Dist: numpy>=1.23.0
Requires-Dist: scipy>=1.6.3
Requires-Dist: matplotlib>=3.3.4
Requires-Dist: numba>=0.55.0
Requires-Dist: mdanalysis>=2.0.0
Requires-Dist: tqdm>=4.45.0
Requires-Dist: pytest>=6.2.2
Requires-Dist: memoization>=0.3.1
Requires-Dist: igraph>=0.10.3
Requires-Dist: rtoml>=0.9.0
Provides-Extra: smiles2residue
Requires-Dist: rdkit>=2023.9.6; extra == "smiles2residue"
Dynamic: license-file
